subreddit_trawler/__init__.py
subreddit_trawler/scraper.py
subreddit_trawler/walker.py
subreddit_trawler-0.0.2.dist-info/METADATA
subreddit_trawler-0.0.2.dist-info/WHEEL
subreddit_trawler-0.0.2.dist-info/licenses/LICENSE
subreddit_trawler-0.0.2.dist-info/RECORD
