Metadata-Version: 2.1
Name: subreddit_trawler
Version: 0.0.2
Summary: Scrape a subreddit's posts.
Project-URL: Homepage, https://github.com/ericlingit/subreddit-trawler
Project-URL: Bug Tracker, https://github.com/ericlingit/subreddit-trawler/issues
Author-email: Eric Lin <ericlingit@users.noreply.github.com>
License-File: LICENSE
Classifier: License :: OSI Approved :: GNU General Public License v3 (GPLv3)
Classifier: Operating System :: OS Independent
Classifier: Programming Language :: Python :: 3
Classifier: Topic :: Utilities
Requires-Python: >=3.7
Requires-Dist: beautifulsoup4
Requires-Dist: lxml
Requires-Dist: requests
